[
  { "beginRendering": { "surfaceId": "dashboardApplication", "root": "root" } },
  { "surfaceUpdate": {
      "components": [
        { "id": "root", "component": { "Column": { "children": { "explicitList": ["html-renderer"] } } } },
        { "id": "html-renderer", "component": {
            "WebFrameSrcdoc": {
                "srcdoc": "<html><body><h1>Hello from A2UI</h1><p>This is rendered in a secure iframe.</p></body></html>",
                "sandbox": "allow-scripts",
                "style": {
                    "height": "300px",
                    "width": "100%"
                }
            }
        } }
      ]
  } }
]
